{
  "skills": [
    {
      "name": "dev-k3s-local-access",
      "domain": "devops",
      "type": "skill",
      "description": "安全配置本地 kubectl 访问华为云开发 k3s 集群：导出远端 kubeconfig、通过 8080 代理接入，并以增量 upsert 方式写入本地 context，避免覆盖现有配置；支持无效 kubeconfig 条目清理。",
      "tags": ["k3s", "kubectl", "kubeconfig", "context", "huawei-cloud", "proxy", "cleanup", "dev-environment"],
      "version": "0.0.1"
    },
    {
      "name": "jumpserver-devops",
      "domain": "devops",
      "type": "skill",
      "description": "通过 JumpServer API 执行开发环境运维操作，支持资产查询、系统用户查询、远程命令执行与日志轮询、SSH 参数获取及临时凭据 SSH 连接。",
      "tags": ["jumpserver", "devops", "ssh", "remote-command", "asset-inventory", "system-user", "api", "automation"],
      "version": "0.0.1"
    },
    {
      "name": "ones-ai-app-builder",
      "domain": "devops",
      "type": "skill",
      "description": "为 ONES AI应用发布平台开发并打包可上传应用，支持静态 ZIP、运行包 ZIP、runtime 选择、manifest.yaml 与 start.sh 生成，以及本地数据库或外接数据库场景。",
      "tags": ["ones", "ai-app", "app-builder", "packaging", "zip", "manifest", "runtime", "deployment"],
      "version": "0.0.1"
    },
    {
      "name": "ones-backend-healthcheck-cli",
      "domain": "devops",
      "type": "skill",
      "description": "在 ONES 单机/集群（K3S/K8S）环境执行后端健康巡检并输出结论，覆盖 Pod 异常、Warning Events、入口与 version API 可达性及异常 Pod 三板斧采集。",
      "tags": ["ones", "k3s", "k8s", "backend", "healthcheck", "pod", "warning-events", "diagnostics"],
      "version": "0.0.1"
    },
    {
      "name": "ones-checklist-validation",
      "domain": "devops",
      "type": "skill",
      "description": "按 ONES 官方 checklist 执行 2.1 登录/登出、2.2 项目管理、2.3 知识库管理核验，不执行 2.4/2.5/3.x 与配置权限类变更。",
      "tags": ["ones", "checklist", "validation", "qa", "project-management", "wiki", "read-only"],
      "version": "0.0.1"
    },
    {
      "name": "ones-k3s-backup-cli",
      "domain": "devops",
      "type": "skill",
      "description": "按官方 backup-Instructions 在 ONES 单机 K3S 执行并验证备份（MinIO/ClickHouse/MySQL/对象存储），包含手动触发与证据化校验。",
      "tags": ["ones", "k3s", "backup", "minio", "clickhouse", "mysql", "object-storage", "disaster-recovery"],
      "version": "0.0.1"
    },
    {
      "name": "ones-k3s-cli-install",
      "domain": "devops",
      "type": "skill",
      "description": "按官方流程在 TTY 模式安装 ONES 单机版 K3S，支持重装前卸载、CLI 方式 init-config、部署回滚观察与 30011 访问验证。",
      "tags": ["ones", "k3s", "install", "single-node", "tty", "init-config", "reinstall", "nodeport-30011"],
      "version": "0.0.1"
    },
    {
      "name": "ones-k3s-envcheck-fix-cli",
      "domain": "devops",
      "type": "skill",
      "description": "执行 K3S envcheck 并按 linux-fix 进行环境修复，修复后复检并输出通过/失败结构化报告。",
      "tags": ["ones", "k3s", "envcheck", "linux-fix", "preflight", "system-tuning", "diagnostics"],
      "version": "0.0.1"
    },
    {
      "name": "ones-k3s-open-multi-team-cli",
      "domain": "devops",
      "type": "skill",
      "description": "按 open-multi-team 文档在 ONES 单机 K3S 环境开启 multi-team，安全执行不可逆 SQL 更新并完成可见性状态验证。",
      "tags": ["ones", "k3s", "multi-team", "sql-update", "visibility", "feature-enable"],
      "version": "0.0.1"
    },
    {
      "name": "ones-k3s-open-telemetry-cli",
      "domain": "devops",
      "type": "skill",
      "description": "按 open-telemetry 文档在 ONES 单机 K3S 开启可观测性（Telemetry/Grafana），支持已开启核验、未开启安装、连通性验证与回滚。",
      "tags": ["ones", "k3s", "telemetry", "grafana", "observability", "monitoring", "port-31380"],
      "version": "0.0.1"
    },
    {
      "name": "ones-k3s-rebuild-kilob-cli",
      "domain": "devops",
      "type": "skill",
      "description": "在 ONES 单机 K3S 执行 Kilob 索引重建、解锁、CDC 重建、PD/TiKV 异常修复与一致性核验，处理索引不一致与锁冲突问题。",
      "tags": ["ones", "k3s", "kilob", "index-rebuild", "cdc", "redis-lock", "tikv", "troubleshooting"],
      "version": "0.0.1"
    },
    {
      "name": "ones-k3s-start-stop-cli",
      "domain": "devops",
      "type": "skill",
      "description": "按 start-stop 文档安全启停 ONES 单机 K3S 服务，包含启停顺序、人工确认恢复与就绪性核验。",
      "tags": ["ones", "k3s", "start-stop", "service-ops", "scale", "readiness", "single-node"],
      "version": "0.0.1"
    },
    {
      "name": "ones-k3s-upgrade-cli",
      "domain": "devops",
      "type": "skill",
      "description": "按官方升级文档在 ONES 单机 K3S 执行升级，覆盖准备、备份、包导入、迁移、2.6/2.7/2.8/2.9 后置步骤与异常人工确认。",
      "tags": ["ones", "k3s", "upgrade", "migration", "backup", "post-upgrade", "release"],
      "version": "0.0.1"
    },
    {
      "name": "ones-plugin",
      "domain": "plugin",
      "type": "skill",
      "description": "ONES OP Plugin（Settings-only）通用交付指引，覆盖开发、调试、打包、升级与最小回归，兼容 Codex 与 OpenClaw。",
      "tags": ["ones", "plugin", "settings", "op", "development", "packup", "upgrade", "codex", "openclaw"],
      "version": "0.0.1"
    }
  ]
}
